beproud.django.basemodels-0.1.0-py2.7-nspkg.pth
beproud/django/basemodels/__init__.py
beproud/django/basemodels/base.py
beproud/django/basemodels/fields.py
beproud.django.basemodels-0.1.0.dist-info/DESCRIPTION.rst
beproud.django.basemodels-0.1.0.dist-info/METADATA
beproud.django.basemodels-0.1.0.dist-info/RECORD
beproud.django.basemodels-0.1.0.dist-info/WHEEL
beproud.django.basemodels-0.1.0.dist-info/metadata.json
beproud.django.basemodels-0.1.0.dist-info/namespace_packages.txt
beproud.django.basemodels-0.1.0.dist-info/top_level.txt
