Metadata-Version: 2.0
Name: beproud.django.basemodels
Version: 0.1.0
Summary: beproud.django.basemodels provides base models and fields, that comes from bpcommons.
Home-page: http://www.beproud.jp/
Author: BeProud Inc.
Author-email: xiao@beproud.jp
License: UNKNOWN
Platform: UNKNOWN
Classifier: Development Status :: 3 - Alpha
Classifier: Environment :: Plugins
Classifier: Framework :: Django
Classifier: Intended Audience :: Developers
Classifier: License :: OSI Approved :: BSD License
Classifier: Programming Language :: Python
Classifier: Topic :: Software Development :: Libraries :: Python Modules
Requires-Dist: django (>=1.8)
